pyallel/__init__.py
pyallel/colours.py
pyallel/constants.py
pyallel/errors.py
pyallel/main.py
pyallel/parser.py
pyallel/printer.py
pyallel/process.py
pyallel/process_group.py
pyallel/process_group_manager.py
pyallel/py.typed
pyallel-2.0.3.dist-info/METADATA
pyallel-2.0.3.dist-info/WHEEL
pyallel-2.0.3.dist-info/entry_points.txt
pyallel-2.0.3.dist-info/licenses/LICENSE
pyallel-2.0.3.dist-info/RECORD
