Metadata-Version: 2.4
Name: pyallel
Version: 2.0.3
Summary: Run and handle the output of multiple executables in pyallel (as in parallel)
License: MIT
License-File: LICENSE
Keywords: parallel,command,runner,executable,shell,terminal
Author: Daniel Black
Author-email: danielcrblack@gmail.com
Requires-Python: >=3.8
Classifier: Development Status :: 5 - Production/Stable
Classifier: License :: OSI Approved :: MIT License
Classifier: Operating System :: MacOS :: MacOS X
Classifier: Operating System :: POSIX :: Linux
Classifier: Programming Language :: Python :: 3
Classifier: Programming Language :: Python :: 3.8
Classifier: Programming Language :: Python :: 3.9
Classifier: Programming Language :: Python :: 3.10
Classifier: Programming Language :: Python :: 3.11
Classifier: Programming Language :: Python :: 3.12
Classifier: Programming Language :: Python :: 3.13
Classifier: Programming Language :: Python :: 3.14
Project-URL: Homepage, https://github.com/Danthewaann/pyallel
Project-URL: Repository, https://github.com/Danthewaann/pyallel
